webpack_loader/__init__.py
webpack_loader/apps.py
webpack_loader/config.py
webpack_loader/contrib/__init__.py
webpack_loader/contrib/jinja2ext.py
webpack_loader/contrib/pages/pageassetfinder.py
webpack_loader/contrib/pages/templatetags/webpack_pages.py
webpack_loader/contrib/pages/utils.py
webpack_loader/errors.py
webpack_loader/exceptions.py
webpack_loader/loader.py
webpack_loader/signals.py
webpack_loader/templatetags/__init__.py
webpack_loader/templatetags/webpack_loader.py
webpack_loader/utils.py
django_webpack5_loader-0.9.1.dist-info/LICENSE
django_webpack5_loader-0.9.1.dist-info/LICENSE.txt
django_webpack5_loader-0.9.1.dist-info/WHEEL
django_webpack5_loader-0.9.1.dist-info/METADATA
django_webpack5_loader-0.9.1.dist-info/RECORD
