Metadata-Version: 2.1
Name: django-webpack5-loader
Version: 0.9.1
Summary: Transparently use webpack with django
Home-page: https://github.com/MrP01/django-webpack-loader
License: MIT
Keywords: django,webpack,assets
Author: MrP01
Author-email: peter@waldert.at
Requires-Python: >=3.9,<4.0
Classifier: License :: OSI Approved :: MIT License
Classifier: Programming Language :: Python :: 3
Classifier: Programming Language :: Python :: 3.9
Classifier: Programming Language :: Python :: 3.10
